pynestor/__init__.py
pynestor/__main__.py
pynestor/default-preview-nestor-cfg.yml
pynestor/preview_odoo_nestor.py
pynestor/pynestor.py
pynestor-1.13.0.dist-info/METADATA
pynestor-1.13.0.dist-info/WHEEL
pynestor-1.13.0.dist-info/top_level.txt
pynestor-1.13.0.dist-info/RECORD
