Metadata-Version: 2.4
Name: pynestor
Version: 1.13.0
Summary: Nestor wrapper in python
Home-page: https://gitlab.mangono.io/python-libs/py-nestor
Author: Alexis Pasquier
Author-email: contact@mangono.fr
Classifier: Programming Language :: Python :: 3
Classifier: Programming Language :: Python :: 3 :: Only
Requires-Python: >=3.8
Requires-Dist: kubernetes>=23.3.0
Requires-Dist: minio<7.2,>=7.1.1
Requires-Dist: python-gitlab<4.0,>=3.2.0
Requires-Dist: pyyaml>=5.3.1
